customer_match/__init__.py
customer_match/cli.py
customer_match_translator-1.0.2.dist-info/LICENSE.txt
customer_match_translator-1.0.2.dist-info/METADATA
customer_match_translator-1.0.2.dist-info/WHEEL
customer_match_translator-1.0.2.dist-info/entry_points.txt
customer_match_translator-1.0.2.dist-info/top_level.txt
customer_match_translator-1.0.2.dist-info/RECORD
