Metadata-Version: 2.1
Name: customer-match-translator
Version: 1.0.2
Summary: A simple command line program to translate a CSV containing customer contact information to Google's Customer Match format.
Home-page: https://github.com/Esquire-Digital/customer-match-tool
Author: Ryan Hartman
Author-email: rhartman1239@gmail.com
License: MIT
Keywords: google customer match csv
Platform: UNKNOWN
Classifier: Development Status :: 4 - Beta
Classifier: Intended Audience :: Developers
Requires-Dist: click
Requires-Dist: pandas
Requires-Dist: uszipcode
Requires-Dist: tqdm
Requires-Dist: phonenumbers
Requires-Dist: country-converter
